{
  "url": "https://us02.procore.com/562949954728542/project/home/ajax_overview_details?domain_name=meetings&filter=open&row_models%5B%5D=MeetingTopic&row_title=Meetings",
  "pageName": "ajax_overview_details?domain_name=meetings&filter=open&row_models%5B%5D=MeetingTopic&row_title=Meetings",
  "category": "emails",
  "pageId": "ajax_overview_details_domain_name_meetings_filter_open_row_models_5b_5d_meetingtopic_row_title_meetings",
  "timestamp": "2026-01-12T16:05:33.023Z",
  "analysis": {
    "components": {
      "buttons": 0,
      "forms": 0,
      "inputs": 0,
      "tables": 1,
      "modals": 0,
      "navigation": 0,
      "cards": 0,
      "lists": 0,
      "tabs": 0,
      "dropdowns": 0,
      "icons": 0,
      "emailList": 0,
      "attachments": 0,
      "recipients": 0,
      "threads": 0,
      "compose": 0
    },
    "tables": [
      {
        "index": 1,
        "headers": [
          "Status",
          "#",
          "Subject",
          "Ball In Court",
          "Due"
        ],
        "rows": 20,
        "classes": "item_list",
        "id": "overview_details"
      }
    ],
    "emailElements": {
      "subjects": [],
      "senders": [],
      "dates": []
    },
    "title": "",
    "h1": "Meetings"
  },
  "links": 40,
  "linkDetails": [
    {
      "href": "https://us02.procore.com/562949954728542/project/meetings/show_meeting_topic/562949972598510",
      "text": "4.1",
      "classes": "",
      "id": null,
      "index": 0
    },
    {
      "href": "https://us02.procore.com/562949954728542/project/meetings/show_meeting_topic/562949972598510",
      "text": "Budget",
      "classes": "",
      "id": null,
      "index": 1
    },
    {
      "href": "https://us02.procore.com/562949954728542/project/meetings/show_meeting_topic/562949972598529",
      "text": "4.2",
      "classes": "",
      "id": null,
      "index": 2
    },
    {
      "href": "https://us02.procore.com/562949954728542/project/meetings/show_meeting_topic/562949972598529",
      "text": "Paint Color",
      "classes": "",
      "id": null,
      "index": 3
    },
    {
      "href": "https://us02.procore.com/562949954728542/project/meetings/show_meeting_topic/562949977674606",
      "text": "1.1",
      "classes": "",
      "id": null,
      "index": 4
    },
    {
      "href": "https://us02.procore.com/562949954728542/project/meetings/show_meeting_topic/562949977674606",
      "text": "Permitting",
      "classes": "",
      "id": null,
      "index": 5
    },
    {
      "href": "https://us02.procore.com/562949954728542/project/meetings/show_meeting_topic/562949977674607",
      "text": "6.1",
      "classes": "",
      "id": null,
      "index": 6
    },
    {
      "href": "https://us02.procore.com/562949954728542/project/meetings/show_meeting_topic/562949977674607",
      "text": "Submittals",
      "classes": "",
      "id": null,
      "index": 7
    },
    {
      "href": "https://us02.procore.com/562949954728542/project/meetings/show_meeting_topic/562949977674608",
      "text": "2.1",
      "classes": "",
      "id": null,
      "index": 8
    },
    {
      "href": "https://us02.procore.com/562949954728542/project/meetings/show_meeting_topic/562949977674608",
      "text": "Material Status",
      "classes": "",
      "id": null,
      "index": 9
    },
    {
      "href": "https://us02.procore.com/562949954728542/project/meetings/show_meeting_topic/562949977674609",
      "text": "7.1",
      "classes": "",
      "id": null,
      "index": 10
    },
    {
      "href": "https://us02.procore.com/562949954728542/project/meetings/show_meeting_topic/562949977674609",
      "text": "RFIs",
      "classes": "",
      "id": null,
      "index": 11
    },
    {
      "href": "https://us02.procore.com/562949954728542/project/meetings/show_meeting_topic/562949977674610",
      "text": "3.1",
      "classes": "",
      "id": null,
      "index": 12
    },
    {
      "href": "https://us02.procore.com/562949954728542/project/meetings/show_meeting_topic/562949977674610",
      "text": "Jobsite Update",
      "classes": "",
      "id": null,
      "index": 13
    },
    {
      "href": "https://us02.procore.com/562949954728542/project/meetings/show_meeting_topic/562949977674611",
      "text": "4.1",
      "classes": "",
      "id": null,
      "index": 14
    },
    {
      "href": "https://us02.procore.com/562949954728542/project/meetings/show_meeting_topic/562949977674611",
      "text": "Schedule",
      "classes": "",
      "id": null,
      "index": 15
    },
    {
      "href": "https://us02.procore.com/562949954728542/project/meetings/show_meeting_topic/562949977674612",
      "text": "5.1",
      "classes": "",
      "id": null,
      "index": 16
    },
    {
      "href": "https://us02.procore.com/562949954728542/project/meetings/show_meeting_topic/562949977674612",
      "text": "Inspections",
      "classes": "",
      "id": null,
      "index": 17
    },
    {
      "href": "https://us02.procore.com/562949954728542/project/meetings/show_meeting_topic/562949977674613",
      "text": "8.1",
      "classes": "",
      "id": null,
      "index": 18
    },
    {
      "href": "https://us02.procore.com/562949954728542/project/meetings/show_meeting_topic/562949977674613",
      "text": "Budget",
      "classes": "",
      "id": null,
      "index": 19
    },
    {
      "href": "https://us02.procore.com/562949954728542/project/meetings/show_meeting_topic/562949980764062",
      "text": "3.3",
      "classes": "",
      "id": null,
      "index": 20
    },
    {
      "href": "https://us02.procore.com/562949954728542/project/meetings/show_meeting_topic/562949980764062",
      "text": "RFIs",
      "classes": "",
      "id": null,
      "index": 21
    },
    {
      "href": "https://us02.procore.com/562949954728542/project/meetings/show_meeting_topic/562949980764356",
      "text": "3.1",
      "classes": "",
      "id": null,
      "index": 22
    },
    {
      "href": "https://us02.procore.com/562949954728542/project/meetings/show_meeting_topic/562949980764356",
      "text": "Contract Change Orders",
      "classes": "",
      "id": null,
      "index": 23
    },
    {
      "href": "https://us02.procore.com/562949954728542/project/meetings/show_meeting_topic/562949980764359",
      "text": "3.2",
      "classes": "",
      "id": null,
      "index": 24
    },
    {
      "href": "https://us02.procore.com/562949954728542/project/meetings/show_meeting_topic/562949980764359",
      "text": "Alleato Change Orders",
      "classes": "",
      "id": null,
      "index": 25
    },
    {
      "href": "https://us02.procore.com/562949954728542/project/meetings/show_meeting_topic/562949980768045",
      "text": "2.1",
      "classes": "",
      "id": null,
      "index": 26
    },
    {
      "href": "https://us02.procore.com/562949954728542/project/meetings/show_meeting_topic/562949980768045",
      "text": "Design Coordination",
      "classes": "",
      "id": null,
      "index": 27
    },
    {
      "href": "https://us02.procore.com/562949954728542/project/meetings/show_meeting_topic/562949980768392",
      "text": "2.2",
      "classes": "",
      "id": null,
      "index": 28
    },
    {
      "href": "https://us02.procore.com/562949954728542/project/meetings/show_meeting_topic/562949980768392",
      "text": "Daycare",
      "classes": "",
      "id": null,
      "index": 29
    },
    {
      "href": "https://us02.procore.com/562949954728542/project/meetings/show_meeting_topic/562949980771561",
      "text": "1.1",
      "classes": "",
      "id": null,
      "index": 30
    },
    {
      "href": "https://us02.procore.com/562949954728542/project/meetings/show_meeting_topic/562949980771561",
      "text": "Including Goodwill in the design meetings",
      "classes": "",
      "id": null,
      "index": 31
    },
    {
      "href": "https://us02.procore.com/562949954728542/project/meetings/show_meeting_topic/562949972597337",
      "text": "1.1",
      "classes": "",
      "id": null,
      "index": 32
    },
    {
      "href": "https://us02.procore.com/562949954728542/project/meetings/show_meeting_topic/562949972597337",
      "text": "Current Schedule",
      "classes": "",
      "id": null,
      "index": 33
    },
    {
      "href": "https://us02.procore.com/562949954728542/project/meetings/show_meeting_topic/562949980771709",
      "text": "1.2",
      "classes": "",
      "id": null,
      "index": 34
    },
    {
      "href": "https://us02.procore.com/562949954728542/project/meetings/show_meeting_topic/562949980771709",
      "text": "Communicate progress with the school",
      "classes": "",
      "id": null,
      "index": 35
    },
    {
      "href": "https://us02.procore.com/562949954728542/project/meetings/show_meeting_topic/562949972598005",
      "text": "2.1",
      "classes": "",
      "id": null,
      "index": 36
    },
    {
      "href": "https://us02.procore.com/562949954728542/project/meetings/show_meeting_topic/562949972598005",
      "text": "Progress",
      "classes": "",
      "id": null,
      "index": 37
    },
    {
      "href": "https://us02.procore.com/562949954728542/project/meetings/show_meeting_topic/562949972598477",
      "text": "3.1",
      "classes": "",
      "id": null,
      "index": 38
    },
    {
      "href": "https://us02.procore.com/562949954728542/project/meetings/show_meeting_topic/562949972598477",
      "text": "Added Scope from permitting",
      "classes": "",
      "id": null,
      "index": 39
    }
  ],
  "clickables": 0,
  "clickableDetails": [],
  "dropdowns": 0,
  "dropdownDetails": [],
  "screenshotPath": "pages/ajax_overview_details_domain_name_meetings_filter_open_row_models_5b_5d_meetingtopic_row_title_meetings/screenshot.png"
}